{
  "en": {
    "signIn": "Sign In",
    "signUp": "Sign Up",
    "financialTracking": "Financial Tracking in",
    "pennyMate": "PennyMate",
    "tagline": "Simple and Friendly.",
    "checkItOut": "Check it out",
    "smarterWay": "A smarter way to manage expenses and incomes",
    "weeklyBudgets": "Weekly, Monthly and Annual Budgets",
    "budgetsDesc": "Personal financial tracking using different independent budgets based on dates of your expenses",
    "stats": "Statistics of Incomes and Expenses",
    "statsDesc": "Ability to track your incomes and expenses in easy way using minimalistic dashboard",
    "transactions": "Transactions history",
    "transactionsDesc": "Adding and visualizing of yours transactions during different periods of time"
  },
  "it": {
    "signIn": "Accedi",
    "signUp": "Registrati",
    "financialTracking": "Monitoraggio Finanziario in",
    "pennyMate": "PennyMate",
    "tagline": "Semplice e Amichevole.",
    "checkItOut": "Scoprilo",
    "smarterWay": "Un modo più intelligente per gestire entrate e uscite",
    "weeklyBudgets": "Budget Settimanali, Mensili e Annuali",
    "budgetsDesc": "Monitoraggio finanziario personale utilizzando budget indipendenti basati sulle date delle tue spese",
    "stats": "Statistiche di Entrate e Uscite",
    "statsDesc": "Possibilità di tracciare entrate e uscite in modo semplice con una dashboard minimalista",
    "transactions": "Cronologia delle Transazioni",
    "transactionsDesc": "Aggiunta e visualizzazione delle tue transazioni durante diversi periodi di tempo"
  },
  "fr": {
    "signIn": "Connexion",
    "signUp": "S'inscrire",
    "financialTracking": "Suivi Financier dans",
    "pennyMate": "PennyMate",
    "tagline": "Simple et Convivial.",
    "checkItOut": "Découvrir",
    "smarterWay": "Une manière plus intelligente de gérer vos revenus et dépenses",
    "weeklyBudgets": "Budgets Hebdomadaires, Mensuels et Annuels",
    "budgetsDesc": "Suivi financier personnel utilisant différents budgets indépendants basés sur les dates de vos dépenses",
    "stats": "Statistiques des Revenus et Dépenses",
    "statsDesc": "Possibilité de suivre vos revenus et dépenses facilement avec un tableau de bord minimaliste",
    "transactions": "Historique des Transactions",
    "transactionsDesc": "Ajout et visualisation de vos transactions sur différentes périodes"
  },
  "es": {
    "signIn": "Iniciar Sesión",
    "signUp": "Registrarse",
    "financialTracking": "Seguimiento Financiero en",
    "pennyMate": "PennyMate",
    "tagline": "Simple y Amigable.",
    "checkItOut": "Descúbrelo",
    "smarterWay": "Una forma más inteligente de gestionar ingresos y gastos",
    "weeklyBudgets": "Presupuestos Semanales, Mensuales y Anuales",
    "budgetsDesc": "Seguimiento financiero personal usando diferentes presupuestos independientes basados en las fechas de tus gastos",
    "stats": "Estadísticas de Ingresos y Gastos",
    "statsDesc": "Capacidad para rastrear tus ingresos y gastos fácilmente con un panel minimalista",
    "transactions": "Historial de Transacciones",
    "transactionsDesc": "Adición y visualización de tus transacciones durante diferentes períodos de tiempo"
  }
}